wellschematicspy/.gitignore
wellschematicspy/__init__.py
wellschematicspy/models.py
wellschematicspy/schematics.py
wellschematicspy-0.1.1.dist-info/LICENSE
wellschematicspy-0.1.1.dist-info/WHEEL
wellschematicspy-0.1.1.dist-info/METADATA
wellschematicspy-0.1.1.dist-info/RECORD
