Metadata-Version: 2.1
Name: wellschematicspy
Version: 0.1.1
Summary: Oil&Gas Well Schematics definition and plot
License: MIT
Author: Santiago Cuervo
Author-email: scuervo91@gmail.com
Requires-Python: >=3.7,<4.0
Classifier: License :: OSI Approved :: MIT License
Classifier: Programming Language :: Python :: 3
Classifier: Programming Language :: Python :: 3.7
Classifier: Programming Language :: Python :: 3.8
Classifier: Programming Language :: Python :: 3.9
Requires-Dist: matplotlib (>=3.4.1,<4.0.0)
Requires-Dist: numpy (>=1.20.2,<2.0.0)
Requires-Dist: pydantic (>=1.8.1,<2.0.0)
